EditorConfig-0.12.2.dist-info/DESCRIPTION.rst
EditorConfig-0.12.2.dist-info/METADATA
EditorConfig-0.12.2.dist-info/RECORD
EditorConfig-0.12.2.dist-info/WHEEL
EditorConfig-0.12.2.dist-info/entry_points.txt
EditorConfig-0.12.2.dist-info/metadata.json
EditorConfig-0.12.2.dist-info/top_level.txt
editorconfig/__init__.py
editorconfig/compat.py
editorconfig/exceptions.py
editorconfig/fnmatch.py
editorconfig/handler.py
editorconfig/ini.py
editorconfig/main.py
editorconfig/versiontools.py
