Metadata-Version: 2.0
Name: EditorConfig
Version: 0.12.2
Summary: EditorConfig File Locator and Interpreter for Python
Home-page: http://editorconfig.org/
Author: EditorConfig Team
Author-email: UNKNOWN
License: python
Platform: UNKNOWN
Classifier: License :: OSI Approved :: Python Software Foundation License
Classifier: Operating System :: OS Independent
Classifier: Programming Language :: Python
Classifier: Programming Language :: Python :: 2.7
Classifier: Programming Language :: Python :: 3
Classifier: Programming Language :: Python :: 3.4
Classifier: Programming Language :: Python :: 3.5
Classifier: Programming Language :: Python :: 3.6
Classifier: Programming Language :: Python :: Implementation :: PyPy
